custom_venv/__init__.py
custom_venv/__main__.py
custom_venv/modulefile.py
custom_venv/python_env.py
custom_venv/tools.py
custom_venv-0.5.4.dist-info/LICENSE
custom_venv-0.5.4.dist-info/METADATA
custom_venv-0.5.4.dist-info/WHEEL
custom_venv-0.5.4.dist-info/top_level.txt
custom_venv-0.5.4.dist-info/RECORD
