Metadata-Version: 2.1
Name: custom-venv
Version: 0.5.4
Summary: To customize Python venv with extra-Python considerations.
Author-email: CEA <roland.lenain@cea.fr>
Maintainer-email: Lenain Roland <roland.lenain@cea.fr>
Project-URL: Homepage, https://codev-tuleap.intra.cea.fr/plugins/git/mp-lpec/custom_python_env
Project-URL: Bug Tracker, https://codev-tuleap.intra.cea.fr/plugins/tracker/?group_id=1037
Classifier: Programming Language :: Python :: 3
Classifier: License :: OSI Approved :: BSD License
Classifier: Development Status :: 4 - Beta
Classifier: Environment :: Console
Classifier: Natural Language :: English
Classifier: Operating System :: POSIX :: Linux
Classifier: Programming Language :: Python :: 3
Classifier: Programming Language :: Unix Shell
Requires-Python: >=3.6
License-File: LICENSE
